{
"type": "FeatureCollection",
"crs": { "type": "name", "properties": { "name": "urn:ogc:def:crs:OGC:1.3:CRS84" } },
                                                                                
"features": [
  { "type": "Feature", "properties": { "OBJECTID_1": 54, "OBJECTID": 151.0, "WEBURL": "http:\/\/www.iolp.gsa.gov\/iolp\/BuildingInfo.asp?bID=DC0458", "NUM": 458, "BLDG_NAME": "Remote Delivery Site", "HSR": null, "GIS_ID": "FED_94", "GSAAREA": 50160.0, "ALIAS": null, "OWNERSHIP": "OWNED", "X": 399622.33, "Y": 132575.44, "ADDRID": 291843, "ADDRESS": "2701 SOUTH CAPITOL STREET SW" }, "geometry": { "type": "Point", "coordinates": [ 
  14.529584, 50.693523 ] } }
]
}


