{
"type": "FeatureCollection",
"crs": { "type": "name", "properties": { "name": "urn:ogc:def:crs:OGC:1.3:CRS84" } },
                                                                                
"features": [
  { "type": "Feature", "properties": { "MEMBER": "Honza Bittner" }, "geometry": { "type": "Point", "coordinates": [ 
  14.529584, 50.693523 ] } }
]
}


